xcc/__init__.py
xcc/_version.py
xcc/commands.py
xcc/connection.py
xcc/device.py
xcc/job.py
xcc/settings.py
xcc/util.py
xanadu_cloud_client-0.3.2.dist-info/LICENSE
xanadu_cloud_client-0.3.2.dist-info/METADATA
xanadu_cloud_client-0.3.2.dist-info/WHEEL
xanadu_cloud_client-0.3.2.dist-info/entry_points.txt
xanadu_cloud_client-0.3.2.dist-info/top_level.txt
xanadu_cloud_client-0.3.2.dist-info/RECORD
